CYuyanChangjianwentiJi094/README.md
CYuyanChangjianwentiJi094/__init__.py
CYuyanChangjianwentiJi094/__main__.py
CYuyanChangjianwentiJi094/file.pdf
CYuyanChangjianwentiJi094/index.html
c_yuyan_changjianwenti_ji_0_9_4-2024.3.1.0.dist-info/METADATA
c_yuyan_changjianwenti_ji_0_9_4-2024.3.1.0.dist-info/WHEEL
c_yuyan_changjianwenti_ji_0_9_4-2024.3.1.0.dist-info/entry_points.txt
c_yuyan_changjianwenti_ji_0_9_4-2024.3.1.0.dist-info/top_level.txt
c_yuyan_changjianwenti_ji_0_9_4-2024.3.1.0.dist-info/RECORD
